auto_climate/__init__.py
auto_climate-0.1.0.dist-info/METADATA
auto_climate-0.1.0.dist-info/WHEEL
auto_climate-0.1.0.dist-info/entry_points.txt
auto_climate-0.1.0.dist-info/top_level.txt
auto_climate-0.1.0.dist-info/RECORD
