Metadata-Version: 2.4
Name: auto-climate
Version: 0.1.0
Summary: An Application for customisable climate control, ideal for reptile enclosures.
Author-email: Adam Pratley <adampratley1@gmail.com>
Requires-Python: >=3.12
